magic_cli/__init__.py
magic_cli/main.py
magic_cli-0.1.23.dist-info/entry_points.txt
magic_cli-0.1.23.dist-info/WHEEL
magic_cli-0.1.23.dist-info/METADATA
magic_cli-0.1.23.dist-info/RECORD
